tdscontrol-0.0.1.dist-info/RECORD
tdscontrol-0.0.1.dist-info/WHEEL
tdscontrol-0.0.1.dist-info/METADATA
tdscontrol-0.0.1.dist-info/licenses/LICENSE
tdscontrol/version.py
tdscontrol/__init__.py
tdscontrol/pytdscontrol.cpython-312-darwin.so
