Metadata-Version: 2.4
Name: tdscontrol
Version: 0.0.1
Summary: A Python wrapper for TDS Control, a library for the analysis
Keywords: Control theory,Dynamical systems,Spectral methods,Time-delay systems
Author-Email: Pieter Appeltans <appeltanspieter@gmail.com>
License-Expression: BSD-3-Clause
License-File: LICENSE
Requires-Python: >=3.9
